lazy_command/__init__.py
lazy_command-0.1.dist-info/DESCRIPTION.rst
lazy_command-0.1.dist-info/METADATA
lazy_command-0.1.dist-info/RECORD
lazy_command-0.1.dist-info/WHEEL
lazy_command-0.1.dist-info/metadata.json
lazy_command-0.1.dist-info/top_level.txt
