Metadata-Version: 2.0
Name: lazy-command
Version: 0.1
Summary: Rust-like command wrapper over subprocess
Home-page: https://github.com/DoumanAsh/lazy-command.py
Author: Douman
Author-email: douman@gmx.se
License: MIT
Platform: UNKNOWN
